ship/__init__.py
ship/__main__.py
ship/colors.py
ship/demo_defer.js
ship/favicon.ico
ship/funkship.py
ship/httpfileserver.py
ship/main.css
ship/shipapp.py
ship/shiperror.py
ship/templates.py
shipapp-0.0.3.1.dist-info/METADATA
shipapp-0.0.3.1.dist-info/WHEEL
shipapp-0.0.3.1.dist-info/entry_points.txt
shipapp-0.0.3.1.dist-info/top_level.txt
shipapp-0.0.3.1.dist-info/RECORD
