Metadata-Version: 2.1
Name: shipapp
Version: 0.0.3.1
Summary: The best way to move files between your devices
Home-page: https://github.com/yusuf8ahmed/Ship
Author: Yusuf Ahmed
Author-email: yusufahmed172@gmail.com
License: UNKNOWN
Keywords: ship shipapp filetransfer shiplite shipu
Platform: UNKNOWN
Classifier: Development Status :: 3 - Alpha
Classifier: Programming Language :: Python :: 3
Classifier: License :: OSI Approved :: MIT License
Classifier: Operating System :: OS Independent
Classifier: Intended Audience :: End Users/Desktop
Classifier: Topic :: Internet :: WWW/HTTP
Classifier: Topic :: Internet :: WWW/HTTP :: Dynamic Content
Requires-Python: >=3
Requires-Dist: qrcode (==6.1)
Requires-Dist: pillow
Requires-Dist: pyngrok
Requires-Dist: loguru
